MANIFEST.in
README.rst
setup.cfg
setup.py
orsaytrace/__init__.py
orsaytrace/trace.py
orsaytrace.egg-info/PKG-INFO
orsaytrace.egg-info/SOURCES.txt
orsaytrace.egg-info/dependency_links.txt
orsaytrace.egg-info/requires.txt
orsaytrace.egg-info/top_level.txt