Metadata-Version: 1.2
Name: orsaytrace
Version: 1.1.3.7
Summary: Flexible ray tracing for optics
Home-page: https://github.com/yvesauad/OrsayTrace
Author: Yves Auad
Author-email: yves.maia-auad@universite-paris-saclay.fr
License: MIT
Download-URL: https://github.com/yvesauad/OrsayTrace/archive/v1.1.3.tar.gz
Project-URL: Documentation, https://orsaytrace.readthedocs.io/en/latest/index.html
Project-URL: Source Code, https://github.com/yvesauad/orsaytrace
Keywords: optics,ray,tracing
Platform: UNKNOWN
Classifier: Development Status :: 3 - Alpha
Classifier: Intended Audience :: Developers
Classifier: Topic :: Software Development :: Build Tools
Classifier: License :: OSI Approved :: MIT License
Classifier: Programming Language :: Python :: 3.9
